{"importBase":"import","nativeBase":"native","name":"basics","deps":[],"uuids":["3000WJUERM05XUlu06XnVe","57hmW0NkNIOpnZ6D7ul0qg","5b7lgaA/JGkYB2EBUur+AU","3000WJUERM05XUlu06XnVe@6c48a"],"paths":{"0":["default/basics_atlas0",1,1],"1":["default/basics_p3zk3r",3,1],"2":["default/basics",0,1],"3":["default/basics_atlas0/texture",2,1]},"scenes":{},"packs":{},"versions":{"import":[0,"ba492",3,"12e46",1,"9cb49",2,"b96a7"],"native":[0,"30a86",1,"550ed",2,"72c38"]},"redirect":[],"debug":false,"extensionMap":{},"hasPreloadScript":true,"dependencyRelationships":{},"types":["cc.BufferAsset","cc.ImageAsset","cc.Texture2D","cc.AudioClip"]}